artux/__init__.py
artux/main.py
artux-0.0.1.dist-info/LICENSE
artux-0.0.1.dist-info/METADATA
artux-0.0.1.dist-info/WHEEL
artux-0.0.1.dist-info/top_level.txt
artux-0.0.1.dist-info/RECORD
