Metadata-Version: 2.1
Name: artux
Version: 0.0.1
Summary: A simple real-time CPU Temperature tracker for Linux systems.
Author-email: bazgab <gabrielbzzt@gmail.com>
Project-URL: Homepage, https://github.com/bazgab/artux
Project-URL: Issues, https://github.com/bazgab/artux/issues
Classifier: Programming Language :: Python :: 3
Classifier: License :: OSI Approved :: MIT License
Classifier: Operating System :: Unix
Requires-Python: >=3.8
License-File: LICENSE
